airline/__init__.py
airline/awsbatch.py
airline/awslambda.py
airline/client.py
airline/event.py
airline/format_exception.py
airline/threadlocal_client.py
airline/version.py
airline-0.5.1.dist-info/LICENSE
airline-0.5.1.dist-info/WHEEL
airline-0.5.1.dist-info/METADATA
airline-0.5.1.dist-info/RECORD
