Metadata-Version: 2.1
Name: airline
Version: 0.5.1
Summary: Lightweight wide event logging to bring more observability to lambda functions.
Home-page: https://github.com/namelessjon/airline
License: UNKNOWN
Author: namelessjon
Author-email: jonathan.stott@gmail.com
Classifier: License :: OSI Approved :: Apache Software License
Classifier: Development Status :: 4 - Beta
Classifier: Intended Audience :: Developers
Requires-Dist: pytest ~=5.3 ; extra == "test"
Requires-Dist: pytest-mock ~=2.0 ; extra == "test"
Provides-Extra: test
